secanalysis/__init__.py
secanalysis/auto_detect.py
secanalysis/sec_formats/__init__.py
secanalysis/sec_formats/base.py
secanalysis/sec_formats/win_gpc.py
secanalysis-0.1.1.dist-info/METADATA
secanalysis-0.1.1.dist-info/WHEEL
secanalysis-0.1.1.dist-info/top_level.txt
secanalysis-0.1.1.dist-info/RECORD
