Metadata-Version: 2.4
Name: secanalysis
Version: 0.1.1
Summary: Add your description here
Requires-Python: >=3.11
Requires-Dist: charset-normalizer>=3.4.1
Requires-Dist: matplotlib>=3.10.1
Requires-Dist: pandas>=2.2.3
Requires-Dist: pybaselines>=1.2.0
Requires-Dist: scipy>=1.15.2
